pmcp/__init__.py
pmcp/__main__.py
pmcp/cli.py
pmcp/errors.py
pmcp/identity.py
pmcp/server.py
pmcp/types.py
pmcp/baml_client/__init__.py
pmcp/baml_client/async_client.py
pmcp/baml_client/config.py
pmcp/baml_client/globals.py
pmcp/baml_client/inlinedbaml.py
pmcp/baml_client/parser.py
pmcp/baml_client/runtime.py
pmcp/baml_client/stream_types.py
pmcp/baml_client/sync_client.py
pmcp/baml_client/tracing.py
pmcp/baml_client/type_builder.py
pmcp/baml_client/type_map.py
pmcp/baml_client/types.py
pmcp/baml_client/watchers.py
pmcp/client/__init__.py
pmcp/client/manager.py
pmcp/config/__init__.py
pmcp/config/guidance.py
pmcp/config/loader.py
pmcp/manifest/__init__.py
pmcp/manifest/code_patterns.yaml
pmcp/manifest/code_patterns_loader.py
pmcp/manifest/environment.py
pmcp/manifest/installer.py
pmcp/manifest/loader.py
pmcp/manifest/manifest.yaml
pmcp/manifest/matcher.py
pmcp/manifest/refresher.py
pmcp/manifest/version_checker.py
pmcp/policy/__init__.py
pmcp/policy/policy.py
pmcp/resources/code_execution_guide.md
pmcp/summary/__init__.py
pmcp/summary/generator.py
pmcp/summary/llm_summarizer.py
pmcp/summary/template_fallback.py
pmcp/templates/code_examples.yaml
pmcp/templates/code_snippets_loader.py
pmcp/tools/__init__.py
pmcp/tools/handlers.py
pmcp-1.2.1.dist-info/METADATA
pmcp-1.2.1.dist-info/WHEEL
pmcp-1.2.1.dist-info/entry_points.txt
pmcp-1.2.1.dist-info/licenses/LICENSE
pmcp-1.2.1.dist-info/RECORD
