Metadata-Version: 2.4
Name: pmcp
Version: 1.2.1
Summary: PMCP - Progressive MCP: Minimal context bloat with on-demand tool discovery
Project-URL: Repository, https://github.com/ViperJuice/pmcp
Project-URL: Homepage, https://github.com/ViperJuice/pmcp
Project-URL: Issues, https://github.com/ViperJuice/pmcp/issues
Author-email: ViperJuice <viperjuice@users.noreply.github.com>
License-Expression: MIT
License-File: LICENSE
Keywords: ai,anthropic,claude,disclosure,llm,mcp,progressive
Classifier: Development Status :: 4 - Beta
Classifier: Intended Audience :: Developers
Classifier: License :: OSI Approved :: MIT License
Classifier: Programming Language :: Python :: 3
Classifier: Programming Language :: Python :: 3.10
Classifier: Programming Language :: Python :: 3.11
Classifier: Programming Language :: Python :: 3.12
Requires-Python: >=3.10
Requires-Dist: aiohttp>=3.9.0
Requires-Dist: mcp>=1.0.0
Requires-Dist: pydantic>=2.0
Requires-Dist: python-dotenv>=1.0.0
Requires-Dist: pyyaml>=6.0
Provides-Extra: all
Requires-Dist: baml-py>=0.215.0; extra == 'all'
Requires-Dist: mypy>=1.0; extra == 'all'
Requires-Dist: pytest-asyncio>=0.21; extra == 'all'
Requires-Dist: pytest-cov>=4.0; extra == 'all'
Requires-Dist: pytest-mock>=3.0; extra == 'all'
Requires-Dist: pytest>=7.0; extra == 'all'
Requires-Dist: ruff>=0.8.0; extra == 'all'
Requires-Dist: types-pyyaml>=6.0; extra == 'all'
Provides-Extra: dev
Requires-Dist: mypy>=1.0; extra == 'dev'
Requires-Dist: pytest-asyncio>=0.21; extra == 'dev'
Requires-Dist: pytest-cov>=4.0; extra == 'dev'
Requires-Dist: pytest-mock>=3.0; extra == 'dev'
Requires-Dist: pytest>=7.0; extra == 'dev'
Requires-Dist: ruff>=0.8.0; extra == 'dev'
Requires-Dist: types-pyyaml>=6.0; extra == 'dev'
Provides-Extra: llm
Requires-Dist: baml-py>=0.215.0; extra == 'llm'
